[
  {
    "desc": [
      "Вы развили навыки, необходимые для того, чтобы держать себя в руках в ближнем бою. Вы получаете следующие преимущества:",
      "- У вас есть преимущество в бросках атаки против существа, которое вы схватили.",
      "- Вы можете действием попытаться удержать схваченное вами существо. Для этого сделайте еще одну проверку захвата. Если вам это удастся, вы и существо будете удержаны до тех пор, пока захват не закончится."
    ],
    "index": "grappler",
    "name": "грепплер",
    "prerequisites": [
      {
        "ability_score": {
          "index": "str",
          "name": "СИЛ",
          "url": "/api/ability-scores/str"
        },
        "minimum_score": 13
      }
    ],
    "url": "/api/feats/grappler"
  }
]